attd.py
attd-1.0.dist-info/METADATA
attd-1.0.dist-info/WHEEL
attd-1.0.dist-info/licenses/AUTHORS.md
attd-1.0.dist-info/licenses/COPYING
attd-1.0.dist-info/RECORD
