Metadata-Version: 2.1
Name: attd
Version: 1.0
Summary: Dictionary with attribute access to keys
Project-URL: Homepage, https://github.com/otsaloma/attd
Author-email: Osmo Salomaa <otsaloma@iki.fi>
License-Expression: MIT
License-File: AUTHORS.md
License-File: COPYING
Requires-Python: >=3.1.0
